azure_requests/__init__.py
azure_requests/py.typed
azure_requests-25.1.dist-info/METADATA
azure_requests-25.1.dist-info/WHEEL
azure_requests-25.1.dist-info/licenses/LICENSE
azure_requests-25.1.dist-info/RECORD
