Metadata-Version: 2.4
Name: azure_requests
Version: 25.1
Summary: Requests wrapper for Azure DevOps
Project-URL: Homepage, https://github.com/presidento/azure-requests
Project-URL: Changelog, https://github.com/presidento/azure-requests/blob/main/CHANGELOG.md
Author-email: Máté Farkas <fm@farkas-mate.hu>
License-Expression: MIT
License-File: LICENSE
Classifier: Development Status :: 5 - Production/Stable
Classifier: Intended Audience :: Developers
Classifier: Intended Audience :: System Administrators
Classifier: Operating System :: OS Independent
Classifier: Programming Language :: Python :: 3 :: Only
Classifier: Programming Language :: Python :: 3.9
Classifier: Programming Language :: Python :: 3.10
Classifier: Programming Language :: Python :: 3.11
Classifier: Programming Language :: Python :: 3.12
Classifier: Programming Language :: Python :: 3.13
Requires-Python: >=3.9
Requires-Dist: requests
